setup.cfg
setup.py
python_opendb.egg-info/PKG-INFO
python_opendb.egg-info/SOURCES.txt
python_opendb.egg-info/dependency_links.txt
python_opendb.egg-info/requires.txt
python_opendb.egg-info/top_level.txt
src/opendb/__init__.py
src/opendb/opendb.py