Metadata-Version: 1.0
Name: python-opendb
Version: 0.1.2
Summary: python interface to http://opendb.netfluid.org
Home-page: https://github.com/riccardocagnasso/python-opendb
Author: Riccardo Cagnasso
Author-email: riccardo@phascode.org
License: MIT
Keywords: python opendb
Platform: UNKNOWN
